schwab_api/__init__.py
schwab_api/account_information.py
schwab_api/authentication.py
schwab_api/schwab.py
schwab_api/totp_generator.py
schwab_api/urls.py
schwab_api2-0.3.0.dist-info/licenses/LICENSE
schwab_api2-0.3.0.dist-info/METADATA
schwab_api2-0.3.0.dist-info/WHEEL
schwab_api2-0.3.0.dist-info/top_level.txt
schwab_api2-0.3.0.dist-info/RECORD
