Metadata-Version: 2.4
Name: schwab_api2
Version: 0.3.0
Summary: Unofficial Schwab API wrapper in Python 3.
Home-page: https://github.com/MaxxRK/schwab-api
Download-URL: https://github.com/itsjafer/schwab-api/tarball/master
Author: Jafer Haider
Author-email: itsjafer@gmail.com
License: MIT
Keywords: schwab,python3,api,unofficial,schwab-api,schwab charles api
Classifier: Development Status :: 3 - Alpha
Classifier: Intended Audience :: Developers
Classifier: Topic :: Software Development :: Build Tools
Classifier: License :: OSI Approved :: MIT License
Classifier: Programming Language :: Python :: 3.7
Classifier: Programming Language :: Python :: 3.8
Classifier: Programming Language :: Python :: 3.9
License-File: LICENSE
Requires-Dist: playwright
Requires-Dist: playwright-sm
Requires-Dist: pyotp
Requires-Dist: python-vipaccess
Dynamic: author
Dynamic: author-email
Dynamic: classifier
Dynamic: description
Dynamic: description-content-type
Dynamic: download-url
Dynamic: home-page
Dynamic: keywords
Dynamic: license
Dynamic: license-file
Dynamic: requires-dist
Dynamic: summary
